{
	"app": {
		"status": "1",
		"toolbar": "true",
		"navigation_drawer": "true",
		"geolocation": "false",
		"cache": "false",
		"open_link_in_external_browser": "false",
		"user_agent": "",
		"privacy_policy_url": "https://sites.google.com/view/mcskincollection",
		"more_apps_url": "https://play.google.com/store/apps/developer?id=Mc+Skin+Collection",
		"redirect_url": ""
	},	
	"menus": [
		{
			"name": "Get free Robux",
			"type": "url",
			"icon": "https://skins2.app.com.tc/others/getrobux/mcskincollection_home.png",
			"url": "https://app.com.tc/mods/category/howtorbx/"
		},
		{
			"name": "Privacy Policy",
			"type": "assets",
			"icon": "https://skins2.app.com.tc/others/getrobux/mcskincollection_privacy.png",
			"url": "mcskincollection_policy.html"
		}
	],
	"notification": {
		"fcm_notification_topic": "webdroid_topic",
		"onesignal_app_id": "00000000-0000-0000-0000-000000000000"
	},
	"ads": {
		"ad_status": "0",
		"ad_type": "admob",
		"backup_ads": "applovin_max",
		"admob_publisher_id": "pub-9466586011189827",
		"admob_app_id": "ca-app-pub-9466586011189827~1166485628",
		"admob_banner_unit_id": "ca-app-pub-9466586011189827/7117650451",
		"admob_interstitial_unit_id": "ca-app-pub-9466586011189827/5804568781",
		"admob_native_unit_id": "ca-app-pub-9466586011189827/4491487117",
		"admob_app_open_ad_unit_id": "ca-app-pub-9466586011189827/3178405441",
		"applovin_banner_ad_unit_id": "33486787d9c7e873",
		"applovin_interstitial_ad_unit_id": "659728f7e4fa25ac",
		"applovin_native_ad_manual_unit_id": "6ba12bf13ca699da",
		"unity_game_id": "5139777",
		"unity_banner_placement_id": "Banner_Android",
		"unity_interstitial_placement_id": "Interstitial_Android",
		"startapp_app_id": "202508278",
		"interstitial_ad_interval": 1
	}
}
